pratyush.py
pratyush-0.1.4.dist-info/licenses/LICENCE
pratyush-0.1.4.dist-info/METADATA
pratyush-0.1.4.dist-info/WHEEL
pratyush-0.1.4.dist-info/entry_points.txt
pratyush-0.1.4.dist-info/top_level.txt
pratyush-0.1.4.dist-info/RECORD
